{
    "_id": "8bcfd726-4fcd-5b2f-b91e-493c61ee9014",
    "name": "Get Bulk Energy",
    "application": {
        "name": "deepmd"
    },
    "properties": [],
    "model": {
        "type": "unknown",
        "subtype": "unknown",
        "method": {
            "type": "unknown",
            "subtype": "unknown",
            "data": {}
        }
    },
    "units": [
        {
            "name": "io-e-bulk",
            "type": "io",
            "subtype": "input",
            "flowchartId": "io-e-bulk",
            "source": "api",
            "input": [
                {
                    "endpoint": "refined-properties",
                    "endpoint_options": {
                        "params": {
                            "query": "{'exabyteId': BULK.exabyteId, 'data.name': 'total_energy', 'group': {'$regex': ''.join((SUBWORKFLOW.application.shortName, ':'))}}",
                            "projection": "{'sort': {'precision.value': -1}, 'limit': 1}"
                        }
                    },
                    "name": "DATA"
                }
            ],
            "status": "idle",
            "statusTrack": [],
            "tags": [],
            "head": true,
            "next": "assign-e-bulk",
            "application": {
                "name": "shell",
                "shortName": "sh",
                "summary": "Shell Script",
                "build": "GNU",
                "isDefault": true,
                "version": "5.1.8",
                "schemaVersion": "2022.8.16"
            }
        },
        {
            "name": "assign-e-bulk",
            "type": "assignment",
            "operand": "E_BULK",
            "value": "DATA[0].data.value if DATA else None",
            "input": [
                {
                    "name": "DATA",
                    "scope": "io-e-bulk"
                }
            ],
            "flowchartId": "assign-e-bulk",
            "status": "idle",
            "statusTrack": [],
            "tags": [],
            "head": false,
            "next": "assert-e-bulk",
            "application": {
                "name": "shell",
                "shortName": "sh",
                "summary": "Shell Script",
                "build": "GNU",
                "isDefault": true,
                "version": "5.1.8",
                "schemaVersion": "2022.8.16"
            }
        },
        {
            "name": "assert-e-bulk",
            "type": "assertion",
            "statement": "E_BULK != None",
            "errorMessage": "Bulk total energy does not exist for the resolved bulk material. Run a bulk total energy workflow first.",
            "flowchartId": "assert-e-bulk",
            "status": "idle",
            "statusTrack": [],
            "tags": [],
            "head": false,
            "application": {
                "name": "shell",
                "shortName": "sh",
                "summary": "Shell Script",
                "build": "GNU",
                "isDefault": true,
                "version": "5.1.8",
                "schemaVersion": "2022.8.16"
            }
        }
    ]
}
